ataleek/__init__.py
ataleek/ataleek.py
ataleek/github_hub.py
ataleek-0.1.data/scripts/ataleek-cli
ataleek-0.1.dist-info/METADATA
ataleek-0.1.dist-info/WHEEL
ataleek-0.1.dist-info/top_level.txt
ataleek-0.1.dist-info/RECORD
