Metadata-Version: 2.1
Name: ataleek
Version: 0.1
Summary: Command Line Interface To Ataleek Platform
Home-page: https://github.com/ataleek/ataleek-cli
Author: Ahmad Bilal Khalid
Author-email: ahmedbilal96@gmail.com
License: MIT
Platform: UNKNOWN
